mdvoxelsegmentation/__init__.py
mdvoxelsegmentation/argparser.py
mdvoxelsegmentation/clustering.py
mdvoxelsegmentation/do_segmentation.py
mdvoxelsegmentation/identity.py
mdvoxelsegmentation/leaflets.py
mdvoxelsegmentation/plotting.py
mdvoxelsegmentation/settests.py
mdvoxelsegmentation/templates/lipid_flip-flop.html
mdvoxelsegmentation/templates/lipid_flip-flop.ipynb
mdvoxelsegmentation/templates/vmd_clusters_visualization.py
mdvoxelsegmentation/templates/vmd_clusters_visualization.vmd
mdvoxelsegmentation-1.1.7.dist-info/AUTHORS.rst
mdvoxelsegmentation-1.1.7.dist-info/LICENSE
mdvoxelsegmentation-1.1.7.dist-info/METADATA
mdvoxelsegmentation-1.1.7.dist-info/WHEEL
mdvoxelsegmentation-1.1.7.dist-info/entry_points.txt
mdvoxelsegmentation-1.1.7.dist-info/top_level.txt
mdvoxelsegmentation-1.1.7.dist-info/RECORD
