Metadata-Version: 2.1
Name: mdvoxelsegmentation
Version: 1.1.7
Summary: Leaflet segmentation of lipids or other amphipathic molecules of olecular dynamics stuctures and trajectories.
Home-page: https://github.com/marrink-lab/MDVoxelSegmentation
Author: BMH Bruininks
Author-email: bartbruininks@gmail.com
Project-URL: Bug Tracker, https://github.com/marrink-lab/MDVoxelSegmentation/issues
Classifier: Programming Language :: Python :: 3
Classifier: License :: OSI Approved :: Apache Software License
Classifier: Operating System :: OS Independent
Requires-Python: >=3.6
License-File: LICENSE
License-File: AUTHORS.rst
Requires-Dist: numpy
Requires-Dist: MDAnalysis
Requires-Dist: psutil
Requires-Dist: matplotlib
